[{"id":"22/015","date":"29/03/2022","no":"8+18+21+35+37+38","sno":"10","sbcode":"","sbnameE":"","sbnameC":"","inv":"26,203,620","p1":"0","p1u":"0.0","p2":"0","p2u":"0.0","p3":"114,390","p3u":"27.5","p4":"9,600","p4u":"114.5","p5":"640","p5u":"2,354.2","p6":"320","p6u":"3,473.3","p7":"40","p7u":"44,748.9"},{"id":"22/014","date":"25/03/2022","no":"15+20+26+28+29+46","sno":"12","sbcode":"","sbnameE":"","sbnameC":"","inv":"33,253,445","p1":"19,936,240","p1u":"1.0","p2":"0","p2u":"0.0","p3":"86,200","p3u":"54.0","p4":"9,600","p4u":"106.0","p5":"640","p5u":"2,002.8","p6":"320","p6u":"3,634.2","p7":"40","p7u":"42,651.4"},{"id":"22/013","date":"22/03/2022","no":"6+28+32+33+40+45","sno":"1","sbcode":"","sbnameE":"","sbnameC":"","inv":"30,987,235","p1":"0","p1u":"0.0","p2":"0","p2u":"0.0","p3":"134,950","p3u":"32.0","p4":"9,600","p4u":"81.3","p5":"640","p5u":"2,153.2","p6":"320","p6u":"3,168.2","p7":"40","p7u":"42,420.7"},{"id":"22/012","date":"18/03/2022","no":"12+18+22+30+40+49","sno":"15","sbcode":"","sbnameE":"","sbnameC":"","inv":"32,834,894","p1":"16,443,330","p1u":"0.5","p2":"568,790","p2u":"2.5","p3":"34,940","p3u":"108.5","p4":"9,600","p4u":"135.0","p5":"640","p5u":"3,736.2","p6":"320","p6u":"3,462.9","p7":"40","p7u":"62,949.4"},{"id":"22/011","date":"15/03/2022","no":"3+10+12+28+39+48","sno":"17","sbcode":"","sbnameE":"","sbnameC":"","inv":"37,122,142","p1":"24,354,680","p1u":"0.5","p2":"1,437,790","p2u":"1.0","p3":"42,360","p3u":"90.5","p4":"9,600","p4u":"193.5","p5":"640","p5u":"4,690.6","p6":"320","p6u":"5,096.7","p7":"40","p7u":"75,553.0"},{"id":"22/010","date":"11/03/2022","no":"11+20+23+29+38+47","sno":"12","sbcode":"","sbnameE":"","sbnameC":"","inv":"34,847,236","p1":"0","p1u":"0.0","p2":"1,527,900","p2u":"1.0","p3":"31,700","p3u":"128.5","p4":"9,600","p4u":"188.0","p5":"640","p5u":"3,106.9","p6":"320","p6u":"5,200.5","p7":"40","p7u":"54,166.6"},{"id":"22/009","date":"08/03/2022","no":"1+5+23+42+46+49","sno":"11","sbcode":"","sbnameE":"","sbnameC":"","inv":"30,478,158","p1":"0","p1u":"0.0","p2":"0","p2u":"0.0","p3":"103,380","p3u":"38.0","p4":"9,600","p4u":"120.0","p5":"640","p5u":"2,071.0","p6":"320","p6u":"4,518.4","p7":"40","p7u":"43,539.0"},{"id":"22/008","date":"03/03/2022","no":"12+19+21+22+40+43","sno":"46","sbcode":"","sbnameE":"","sbnameC":"","inv":"29,256,378","p1":"0","p1u":"0.0","p2":"0","p2u":"0.0","p3":"160,450","p3u":"26.0","p4":"9,600","p4u":"69.0","p5":"640","p5u":"1,955.2","p6":"320","p6u":"2,153.5","p7":"40","p7u":"43,365.1"},{"id":"22/007","date":"24/02/2022","no":"2+9+11+12+16+24","sno":"43","sbcode":"","sbnameE":"","sbnameC":"","inv":"35,209,894","p1":"9,812,450","p1u":"1.0","p2":"173,900","p2u":"2.0","p3":"19,200","p3u":"288.0","p4":"9,600","p4u":"191.0","p5":"640","p5u":"8,887.6","p6":"320","p6u":"4,577.0","p7":"40","p7u":"112,189.8"},{"id":"22/006","date":"17/02/2022","no":"6+7+22+34+35+46","sno":"8","sbcode":"","sbnameE":"","sbnameC":"","inv":"33,908,375","p1":"0","p1u":"0.0","p2":"1,538,020","p2u":"0.5","p3":"92,160","p3u":"44.5","p4":"9,600","p4u":"191.5","p5":"640","p5u":"2,524.5","p6":"320","p6u":"4,958.5","p7":"40","p7u":"50,052.8"},{"id":"22/005","date":"10/02/2022","no":"6+13+17+28+35+44","sno":"5","sbcode":"","sbnameE":"","sbnameC":"","inv":"43,149,524","p1":"21,313,080","p1u":"1.0","p2":"0","p2u":"0.0","p3":"75,830","p3u":"69.5","p4":"9,600","p4u":"194.0","p5":"640","p5u":"3,652.2","p6":"320","p6u":"6,184.3","p7":"40","p7u":"66,054.7"},{"id":"22/004","date":"05/02/2022","no":"15+18+21+25+39+43","sno":"33","sbcode":"","sbnameE":"","sbnameC":"","inv":"46,064,752","p1":"0","p1u":"0.0","p2":"1,230,600","p2u":"2.0","p3":"128,690","p3u":"51.0","p4":"9,600","p4u":"132.0","p5":"640","p5u":"2,789.5","p6":"320","p6u":"4,572.6","p7":"40","p7u":"58,211.0"},{"id":"22/003","date":"27/01/2022","no":"10+18+20+29+32+33","sno":"2","sbcode":"","sbnameE":"","sbnameC":"","inv":"37,926,197","p1":"0","p1u":"0.0","p2":"824,960","p2u":"2.0","p3":"61,530","p3u":"71.5","p4":"9,600","p4u":"216.0","p5":"640","p5u":"3,412.2","p6":"320","p6u":"5,370.5","p7":"40","p7u":"60,419.1"},{"id":"22/002","date":"20/01/2022","no":"1+3+10+11+30+42","sno":"39","sbcode":"","sbnameE":"","sbnameC":"","inv":"315,247,031","p1":"17,446,020","p1u":"7.0","p2":"2,083,190","p2u":"6.0","p3":"39,460","p3u":"844.5","p4":"9,600","p4u":"1,346.0","p5":"640","p5u":"42,689.7","p6":"320","p6u":"36,260.0","p7":"40","p7u":"670,456.5"},{"id":"22/001","date":"04/01/2022","no":"2+8+12+14+20+47","sno":"36","sbcode":"SBD","sbnameE":"New Year Snowball","sbnameC":"新年金多寶","inv":"182,618,372","p1":"0","p1u":"0.0","p2":"1,824,050","p2u":"4.5","p3":"62,620","p3u":"349.5","p4":"9,600","p4u":"661.0","p5":"640","p5u":"19,225.6","p6":"320","p6u":"20,417.2","p7":"40","p7u":"332,422.3"}]
